[
    {
     "title": "Teclado",
     "price": 199,
     "thumbnail": "https://cdn.pixabay.com/photo/2013/07/12/17/41/computer-mouse-152249_960_720.png",
     "description": "Cerveza rubia americana. Presentación en envase de vidrio. Volumen: 1lt",
     "code": "A543",
     "stock": 23,
     "id": 1,
     "timestamp": "30/9/2022 15:04:18"
    },
    {
     "title": "Mouse",
     "price": 217,
     "thumbnail": "https://cdn.pixabay.com/photo/2013/07/12/17/41/computer-mouse-152249_960_720.png",
     "description": "Cerveza rubia argentina. Presentación en envase de vidrio. Volumen: 1lt",
     "code": "A540",
     "stock": 20,
     "id": 2,
     "timestamp": "30/9/2022 15:26:08"
    },
    {
     "title": "Placa madre",
     "price": 217,
     "thumbnail": "https://cdn.pixabay.com/photo/2013/07/12/17/41/computer-mouse-152249_960_720.png",
     "description": "Cerveza rubia brasileña. Presentación en envase de vidrio. Volumen: 1lt",
     "code": "A541",
     "stock": 17,
     "id": 3,
     "timestamp": "30/9/2022 15:26:31"
    },
    {
     "title": "Monitor",
     "price": 162,
     "thumbnail": "https://cdn.pixabay.com/photo/2013/07/12/17/41/computer-mouse-152249_960_720.png",
     "description": "Cerveza rubia Andes. Presentación en envase de lata. Volumen: 473ml",
     "code": "A542",
     "stock": 28,
     "id": 4,
     "timestamp": "30/9/2022 15:27:45"
    },
    {
     "title": "Auricular",
     "price": 141.67,
     "thumbnail": "https://cdn.pixabay.com/photo/2013/07/12/17/41/computer-mouse-152249_960_720.png",
     "description": "Cerveza negra stout. Presentación en envase de lata. Volumen: 473ml",
     "code": "A540",
     "stock": 21,
     "id": 5,
     "timestamp": "30/9/2022 15:29:37"
    }
   ]